getevent_sendevent/LICENSE
getevent_sendevent/README.MD
getevent_sendevent/__init__.py
getevent_sendevent/requirements.txt
getevent_sendevent/thirdparty.json
getevent_sendevent-0.10.dist-info/LICENSE.rst
getevent_sendevent-0.10.dist-info/METADATA
getevent_sendevent-0.10.dist-info/WHEEL
getevent_sendevent-0.10.dist-info/top_level.txt
getevent_sendevent-0.10.dist-info/RECORD
