Metadata-Version: 2.1
Name: getevent-sendevent
Version: 0.10
Summary: Converts getevent (ADB) into sendevent/binary, output can be saved, loaded and executed. Execution speed can be defined.
Home-page: https://github.com/hansalemaos/getevent_sendevent
Author: Johannes Fischer
Author-email: <aulasparticularesdealemaosp@gmail.com>
License: MIT
Keywords: bluestacks,adb,touch,tap,getevent,sendevent
Classifier: Development Status :: 4 - Beta
Classifier: Programming Language :: Python :: 3 :: Only
Classifier: Programming Language :: Python :: 3.9
Classifier: Topic :: Scientific/Engineering :: Visualization
Classifier: Topic :: Software Development :: Libraries :: Python Modules
Classifier: Topic :: Text Editors :: Text Processing
Classifier: Topic :: Text Processing :: General
Classifier: Topic :: Text Processing :: Indexing
Classifier: Topic :: Text Processing :: Filters
Classifier: Topic :: Utilities
License-File: LICENSE.rst
